{
    "title": "548-Green Tree: Reported Location + 3 Mile Buffer",
    "subtitle": "Attributes Updated: September 23, 12:04 AKDT",
    "data": {
        "Alaska Known Sites": 44.564729767455255,
        "FEMA Structures": 87.51815754716901,
        "Native Allotments": null,
        "Communities": 100.0,
        "Population Count": 94.29188295211229,
        "Timber Value": null,
        "Critical Infrastructure": 75.59843224412003,
        "Major Roads": 96.30267041124758,
        "Road Closures": null
    },
    "raw": {
        "Critical Infrastructure": [
            {
                "value": 295224,
                "metric": "feet"
            },
            {
                "value": 6,
                "metric": "features"
            }
        ],
        "Major Roads": {
            "value": 62148,
            "metric": "feet"
        },
        "Timber Value": {
            "value": null,
            "metric": "$"
        },
        "Native Allotments": {
            "value": null,
            "metric": "allotments"
        },
        "Population Count": {
            "value": 1280.98,
            "metric": "people"
        },
        "Communities": {
            "value": 3,
            "metric": "community boundaries"
        },
        "Road Closures": {
            "value": null,
            "metric": "closures"
        },
        "FEMA Structures": {
            "value": 816,
            "metric": "structures"
        },
        "Alaska Known Sites": {
            "value": 11,
            "metric": "structures"
        }
    }
}