{
    "title": "268-Aggie Creek: Perimeter + 1 Mile Buffer",
    "subtitle": "Perimeter Updated: September 22, 08:22 AKDT",
    "data": {
        "Alaska Known Sites": 32.33924087028423,
        "FEMA Structures": null,
        "Native Allotments": null,
        "Communities": null,
        "Population Count": null,
        "Timber Value": 0.0,
        "Critical Infrastructure": 93.106954056185,
        "Major Roads": 85.78077475446572,
        "Road Closures": null
    },
    "raw": {
        "Critical Infrastructure": [
            {
                "value": 34408,
                "metric": "feet"
            },
            {
                "value": 2,
                "metric": "features"
            }
        ],
        "Major Roads": {
            "value": 10809,
            "metric": "feet"
        },
        "Timber Value": {
            "value": 0,
            "metric": "$"
        },
        "Native Allotments": {
            "value": null,
            "metric": "allotments"
        },
        "Population Count": {
            "value": null,
            "metric": "people"
        },
        "Communities": {
            "value": null,
            "metric": "community boundaries"
        },
        "Road Closures": {
            "value": null,
            "metric": "closures"
        },
        "FEMA Structures": {
            "value": null,
            "metric": "structures"
        },
        "Alaska Known Sites": {
            "value": 4,
            "metric": "structures"
        }
    }
}